[
  {
    "EstimatedRestorationTime": "2026-07-22T02:41:30",
    "DispatchedTime": "2026-07-21T07:42:53",
    "EventId": "J.26.0144915",
    "Type": "Unplanned",
    "Status": "Completed",
    "Cause": "Network equipment fault",
    "StartTime": "2026-07-21T17:12:26",
    "RestorationTime": "2026-07-22T01:04:28",
    "ImpactedCustomers": 0,
    "LocationGeoJson": null,
    "Location": null,
    "ImpactedSuburbs": [],
    "ImpactedAreaGeoJson": null,
    "ImpactedArea": null,
    "LastUpdatedTime": "2026-07-22T05:40:49.237Z",
    "FeedReceivedTime": "2026-07-21T21:10:45.925Z",
    "History": [
      {
        "ImpactedSuburbs": [
          {
            "SuburbName": "SUNBURY",
            "PostCode": 3429,
            "Streets": [
              "LOLLIPOP CR",
              "MONTEGO BVD",
              "SPACES ST"
            ]
          }
        ],
        "ImpactedAreaGeoJson": {
          "type": "Feature",
          "properties": {
            "type": "Historical",
            "customersOff": 26,
            "eventId": "J.26.0144915",
            "startTime": "2026-07-21T17:12:26",
            "restoreTime": "2026-07-22T01:04:28",
            "suburbs": [
              {
                "suburbName": "SUNBURY",
                "postcode": 3429,
                "streets": [
                  "LOLLIPOP CR",
                  "MONTEGO BVD",
                  "SPACES ST"
                ]
              }
            ]
          },
          "geometry": {
            "type": "Polygon",
            "coordinates": [
              [
                [
                  144.76466670037473,
                  -37.57656255816381
                ],
                [
                  144.7636916360283,
                  -37.57633009513588
                ],
                [
                  144.76364864611577,
                  -37.576303618512284
                ],
                [
                  144.763637723699,
                  -37.576272102162264
                ],
                [
                  144.76364499192192,
                  -37.57546531654858
                ],
                [
                  144.7636679909774,
                  -37.575422614730556
                ],
                [
                  144.76372250819585,
                  -37.57540562063764
                ],
                [
                  144.7645494321989,
                  -37.57541976749073
                ],
                [
                  144.76503612362765,
                  -37.575457567373356
                ],
                [
                  144.76569355036355,
                  -37.575801047469106
                ],
                [
                  144.76570649841926,
                  -37.575835068509576
                ],
                [
                  144.76569992596785,
                  -37.57657381869512
                ],
                [
                  144.76567493539977,
                  -37.576618002012005
                ],
                [
                  144.76561695703091,
                  -37.576633267344704
                ],
                [
                  144.76466670037473,
                  -37.57656255816381
                ]
              ]
            ]
          }
        },
        "ImpactedArea": [
          [
            {
              "Latitude": -37.57656255816381,
              "Longitude": 144.76466670037473
            },
            {
              "Latitude": -37.57633009513588,
              "Longitude": 144.7636916360283
            },
            {
              "Latitude": -37.576303618512284,
              "Longitude": 144.76364864611577
            },
            {
              "Latitude": -37.576272102162264,
              "Longitude": 144.763637723699
            },
            {
              "Latitude": -37.57546531654858,
              "Longitude": 144.76364499192192
            },
            {
              "Latitude": -37.575422614730556,
              "Longitude": 144.7636679909774
            },
            {
              "Latitude": -37.57540562063764,
              "Longitude": 144.76372250819585
            },
            {
              "Latitude": -37.57541976749073,
              "Longitude": 144.7645494321989
            },
            {
              "Latitude": -37.575457567373356,
              "Longitude": 144.76503612362765
            },
            {
              "Latitude": -37.575801047469106,
              "Longitude": 144.76569355036355
            },
            {
              "Latitude": -37.575835068509576,
              "Longitude": 144.76570649841926
            },
            {
              "Latitude": -37.57657381869512,
              "Longitude": 144.76569992596785
            },
            {
              "Latitude": -37.576618002012005,
              "Longitude": 144.76567493539977
            },
            {
              "Latitude": -37.576633267344704,
              "Longitude": 144.76561695703091
            },
            {
              "Latitude": -37.57656255816381,
              "Longitude": 144.76466670037473
            }
          ]
        ],
        "RestorationTime": "2026-07-22T01:04:28",
        "ImpactedCustomers": 26,
        "LocationGeoJson": {
          "type": "Feature",
          "properties": {
            "type": "Historical",
            "customersOff": 26,
            "eventId": "J.26.0144915",
            "startTime": "2026-07-21T17:12:26",
            "restoreTime": "2026-07-22T01:04:28",
            "suburbs": [
              {
                "suburbName": "SUNBURY",
                "postcode": 3429,
                "streets": [
                  "LOLLIPOP CR",
                  "MONTEGO BVD",
                  "SPACES ST"
                ]
              }
            ]
          },
          "geometry": {
            "type": "Point",
            "coordinates": [
              144.76467211105913,
              -37.57601944399117
            ]
          }
        },
        "Location": {
          "Latitude": -37.57601944399117,
          "Longitude": 144.76467211105913
        }
      }
    ]
  },
  {
    "EstimatedRestorationTime": "2026-07-21T18:28:38",
    "DispatchedTime": "2026-07-21T05:09:39",
    "EventId": "J.26.0144885",
    "Type": "Unplanned",
    "Status": "Completed",
    "Cause": "Network equipment fault",
    "StartTime": "2026-07-21T14:28:26",
    "RestorationTime": "2026-07-21T20:07:35",
    "ImpactedCustomers": 0,
    "LocationGeoJson": null,
    "Location": null,
    "ImpactedSuburbs": [],
    "ImpactedAreaGeoJson": null,
    "ImpactedArea": null,
    "LastUpdatedTime": "2026-07-22T05:40:49.237Z",
    "FeedReceivedTime": "2026-07-21T21:14:18.936Z",
    "History": [
      {
        "ImpactedSuburbs": [
          {
            "SuburbName": "MACLEOD",
            "PostCode": 3085,
            "Streets": [
              "HIGHVIEW CR",
              "THORNTON ST"
            ]
          }
        ],
        "ImpactedAreaGeoJson": {
          "type": "Feature",
          "properties": {
            "type": "Historical",
            "customersOff": 14,
            "eventId": "J.26.0144885",
            "startTime": "2026-07-21T14:28:26",
            "restoreTime": "2026-07-21T20:07:35",
            "suburbs": [
              {
                "suburbName": "MACLEOD",
                "postcode": 3085,
                "streets": [
                  "HIGHVIEW CR",
                  "THORNTON ST"
                ]
              }
            ]
          },
          "geometry": {
            "type": "Polygon",
            "coordinates": [
              [
                [
                  145.0672434812093,
                  -37.718130321538794
                ],
                [
                  145.0672421422622,
                  -37.71809408721077
                ],
                [
                  145.06726272395045,
                  -37.71805269293646
                ],
                [
                  145.0674753078812,
                  -37.717809411396665
                ],
                [
                  145.06753323915223,
                  -37.71779115890134
                ],
                [
                  145.06875425303528,
                  -37.718448350922266
                ],
                [
                  145.068777290464,
                  -37.718493433148005
                ],
                [
                  145.06844088616074,
                  -37.71877768350549
                ],
                [
                  145.06838898021735,
                  -37.718790238340304
                ],
                [
                  145.06729341445657,
                  -37.718190534679955
                ],
                [
                  145.0672434812093,
                  -37.718130321538794
                ]
              ]
            ]
          }
        },
        "ImpactedArea": [
          [
            {
              "Latitude": -37.718130321538794,
              "Longitude": 145.0672434812093
            },
            {
              "Latitude": -37.71809408721077,
              "Longitude": 145.0672421422622
            },
            {
              "Latitude": -37.71805269293646,
              "Longitude": 145.06726272395045
            },
            {
              "Latitude": -37.717809411396665,
              "Longitude": 145.0674753078812
            },
            {
              "Latitude": -37.71779115890134,
              "Longitude": 145.06753323915223
            },
            {
              "Latitude": -37.718448350922266,
              "Longitude": 145.06875425303528
            },
            {
              "Latitude": -37.718493433148005,
              "Longitude": 145.068777290464
            },
            {
              "Latitude": -37.71877768350549,
              "Longitude": 145.06844088616074
            },
            {
              "Latitude": -37.718790238340304,
              "Longitude": 145.06838898021735
            },
            {
              "Latitude": -37.718190534679955,
              "Longitude": 145.06729341445657
            },
            {
              "Latitude": -37.718130321538794,
              "Longitude": 145.0672434812093
            }
          ]
        ],
        "RestorationTime": "2026-07-21T20:07:35",
        "ImpactedCustomers": 14,
        "LocationGeoJson": {
          "type": "Feature",
          "properties": {
            "type": "Historical",
            "customersOff": 14,
            "eventId": "J.26.0144885",
            "startTime": "2026-07-21T14:28:26",
            "restoreTime": "2026-07-21T20:07:35",
            "suburbs": [
              {
                "suburbName": "MACLEOD",
                "postcode": 3085,
                "streets": [
                  "HIGHVIEW CR",
                  "THORNTON ST"
                ]
              }
            ]
          },
          "geometry": {
            "type": "Point",
            "coordinates": [
              145.0680097163631,
              -37.71829069862082
            ]
          }
        },
        "Location": {
          "Latitude": -37.71829069862082,
          "Longitude": 145.0680097163631
        }
      }
    ]
  },
  {
    "PlannedStartTime": "2026-07-22T08:00:00",
    "PlannedEndTime": "2026-07-22T17:30:00",
    "EventId": "J.26.0143071",
    "Type": "Planned",
    "Status": "Planned Outage Execution",
    "Cause": "Essential Maintenance",
    "StartTime": "2026-07-22T09:25:14",
    "RestorationTime": null,
    "ImpactedCustomers": 6,
    "LocationGeoJson": {
      "type": "Feature",
      "properties": {
        "eventId": "J.26.0143071",
        "customerReference": "J5221708",
        "customersOff": "6",
        "status": "Planned Outage Execution",
        "type": "Planned",
        "resolvedFlag": "false",
        "showOutageFlag": "false",
        "symptoms": [],
        "cause": "Essential Maintenance",
        "startTime": "2026-07-22T09:25:14",
        "restoreTime": "",
        "dispatchedTime": "",
        "etr": "2026-07-22T17:30:00",
        "plannedStartTime": "2026-07-22T08:00:00",
        "plannedEndTime": "2026-07-22T17:30:00",
        "lastUpdateTime": "2026-07-22T09:25:25"
      },
      "geometry": {
        "type": "Point",
        "coordinates": [
          144.8799563458537,
          -37.700605304466904
        ]
      }
    },
    "Location": {
      "Latitude": -37.700605304466904,
      "Longitude": 144.8799563458537
    },
    "ImpactedSuburbs": [
      {
        "SuburbName": "TULLAMARINE",
        "PostCode": 3043,
        "Streets": [
          "BROADMEADOWS RD",
          "THERESA ST"
        ]
      }
    ],
    "ImpactedAreaGeoJson": {
      "type": "Feature",
      "properties": {
        "eventId": "J.26.0143071",
        "customerReference": "J5221708",
        "customersOff": "6",
        "status": "Planned Outage Execution",
        "type": "Planned",
        "resolvedFlag": "false",
        "showOutageFlag": "false",
        "symptoms": [],
        "cause": "Essential Maintenance",
        "startTime": "2026-07-22T09:25:14",
        "restoreTime": "",
        "dispatchedTime": "",
        "etr": "2026-07-22T17:30:00",
        "plannedStartTime": "2026-07-22T08:00:00",
        "plannedEndTime": "2026-07-22T17:30:00",
        "lastUpdateTime": "2026-07-22T09:25:25"
      },
      "geometry": {
        "type": "Polygon",
        "coordinates": [
          [
            [
              144.87949730236733,
              -37.701006342173514
            ],
            [
              144.87946921313946,
              -37.70098015519217
            ],
            [
              144.87939122226302,
              -37.70080328447132
            ],
            [
              144.87944954026142,
              -37.70048471139599
            ],
            [
              144.8797279365882,
              -37.69994427552092
            ],
            [
              144.87978215423098,
              -37.69992942789788
            ],
            [
              144.88001283126394,
              -37.69995910079497
            ],
            [
              144.88004160113638,
              -37.69998717439152
            ],
            [
              144.88050141247768,
              -37.70113104715092
            ],
            [
              144.8805214694444,
              -37.70125042109883
            ],
            [
              144.88049965546404,
              -37.70127246870902
            ],
            [
              144.88045429128076,
              -37.701281181035924
            ],
            [
              144.87999637064473,
              -37.70122784391285
            ],
            [
              144.87949730236733,
              -37.701006342173514
            ]
          ]
        ]
      }
    },
    "ImpactedArea": [
      [
        {
          "Latitude": -37.701006342173514,
          "Longitude": 144.87949730236733
        },
        {
          "Latitude": -37.70098015519217,
          "Longitude": 144.87946921313946
        },
        {
          "Latitude": -37.70080328447132,
          "Longitude": 144.87939122226302
        },
        {
          "Latitude": -37.70048471139599,
          "Longitude": 144.87944954026142
        },
        {
          "Latitude": -37.69994427552092,
          "Longitude": 144.8797279365882
        },
        {
          "Latitude": -37.69992942789788,
          "Longitude": 144.87978215423098
        },
        {
          "Latitude": -37.69995910079497,
          "Longitude": 144.88001283126394
        },
        {
          "Latitude": -37.69998717439152,
          "Longitude": 144.88004160113638
        },
        {
          "Latitude": -37.70113104715092,
          "Longitude": 144.88050141247768
        },
        {
          "Latitude": -37.70125042109883,
          "Longitude": 144.8805214694444
        },
        {
          "Latitude": -37.70127246870902,
          "Longitude": 144.88049965546404
        },
        {
          "Latitude": -37.701281181035924,
          "Longitude": 144.88045429128076
        },
        {
          "Latitude": -37.70122784391285,
          "Longitude": 144.87999637064473
        },
        {
          "Latitude": -37.701006342173514,
          "Longitude": 144.87949730236733
        }
      ]
    ],
    "LastUpdatedTime": "2026-07-22T05:40:49.237Z",
    "FeedReceivedTime": "2026-07-21T23:27:17.045Z",
    "History": null
  },
  {
    "PlannedStartTime": "2026-07-22T07:30:00",
    "PlannedEndTime": "2026-07-22T17:30:00",
    "EventId": "J.26.0142896",
    "Type": "Planned",
    "Status": "Planned Outage Execution",
    "Cause": "Essential Maintenance",
    "StartTime": "2026-07-22T08:47:51",
    "RestorationTime": "2026-07-22T14:34:15",
    "ImpactedCustomers": 90,
    "LocationGeoJson": null,
    "Location": null,
    "ImpactedSuburbs": [],
    "ImpactedAreaGeoJson": null,
    "ImpactedArea": null,
    "LastUpdatedTime": "2026-07-22T05:40:49.237Z",
    "FeedReceivedTime": "2026-07-22T04:37:32.887Z",
    "History": [
      {
        "ImpactedSuburbs": [
          {
            "SuburbName": "CALDER PARK",
            "PostCode": 3037,
            "Streets": [
              "CALDER FWY"
            ]
          },
          {
            "SuburbName": "DIGGERS REST",
            "PostCode": 3427,
            "Streets": [
              "CALDER HIGHWAY",
              "DILLON CT",
              "HOLDEN RD",
              "MARK COURT",
              "THOMPSONS RD"
            ]
          },
          {
            "SuburbName": "KEILOR NORTH",
            "PostCode": 3036,
            "Streets": [
              "CALDER FREEWAY",
              "CALDER FWY",
              "THOMPSONS RD"
            ]
          },
          {
            "SuburbName": "PLUMPTON",
            "PostCode": 3335,
            "Streets": [
              "HOLDEN RD"
            ]
          }
        ],
        "ImpactedAreaGeoJson": {
          "type": "Feature",
          "properties": {
            "type": "Historical",
            "customersOff": 35,
            "eventId": "J.26.0142896",
            "startTime": "2026-07-22T08:47:51",
            "restoreTime": "2026-07-22T14:34:08",
            "suburbs": [
              {
                "suburbName": "CALDER PARK",
                "postcode": 3037,
                "streets": [
                  "CALDER FWY"
                ]
              },
              {
                "suburbName": "DIGGERS REST",
                "postcode": 3427,
                "streets": [
                  "CALDER HIGHWAY",
                  "DILLON CT",
                  "HOLDEN RD",
                  "MARK COURT",
                  "THOMPSONS RD"
                ]
              },
              {
                "suburbName": "KEILOR NORTH",
                "postcode": 3036,
                "streets": [
                  "CALDER FREEWAY",
                  "CALDER FWY",
                  "THOMPSONS RD"
                ]
              },
              {
                "suburbName": "PLUMPTON",
                "postcode": 3335,
                "streets": [
                  "HOLDEN RD"
                ]
              }
            ]
          },
          "geometry": {
            "type": "Polygon",
            "coordinates": [
              [
                [
                  144.7590489123732,
                  -37.680548589859384
                ],
                [
                  144.75872129846167,
                  -37.680811038514506
                ],
                [
                  144.7583321120861,
                  -37.68101410130429
                ],
                [
                  144.7578982273339,
                  -37.681148974481914
                ],
                [
                  144.75743845629526,
                  -37.681209810686944
                ],
                [
                  144.7569727334209,
                  -37.6811939724059
                ],
                [
                  144.71802128809077,
                  -37.67662159179456
                ],
                [
                  144.71759652559328,
                  -37.67653746755044
                ],
                [
                  144.71720057629196,
                  -37.676389513643166
                ],
                [
                  144.71684858675158,
                  -37.67618338951141
                ],
                [
                  144.71655402190905,
                  -37.67592697973994
                ],
                [
                  144.71632814998847,
                  -37.67563009251197
                ],
                [
                  144.7161796114487,
                  -37.6753040844793
                ],
                [
                  144.71611408845314,
                  -37.674961426389686
                ],
                [
                  144.71613408750525,
                  -37.67461522607846
                ],
                [
                  144.71875619253225,
                  -37.66027266757495
                ],
                [
                  144.72469701046904,
                  -37.63430121079435
                ],
                [
                  144.724818269932,
                  -37.633964748424184
                ],
                [
                  144.72502061017695,
                  -37.63365369719269
                ],
                [
                  144.72529614983623,
                  -37.63338017326614
                ],
                [
                  144.72563415634716,
                  -37.633154831159324
                ],
                [
                  144.72602146399674,
                  -37.63298644865894
                ],
                [
                  144.72644298674032,
                  -37.63288158484657
                ],
                [
                  144.72688230581883,
                  -37.63284432455316
                ],
                [
                  144.72732230928713,
                  -37.632876119208206
                ],
                [
                  144.72779326428747,
                  -37.632947783838794
                ],
                [
                  144.72817075630633,
                  -37.6330329762231
                ],
                [
                  144.72852365706652,
                  -37.633169073217324
                ],
                [
                  144.7390908756035,
                  -37.63819610146118
                ],
                [
                  144.73944425474355,
                  -37.63840422032743
                ],
                [
                  144.73973934608313,
                  -37.63866309332048
                ],
                [
                  144.76566337106786,
                  -37.66647495259233
                ],
                [
                  144.76588269652945,
                  -37.666764312102664
                ],
                [
                  144.7660287540973,
                  -37.667081333668435
                ],
                [
                  144.76609624771316,
                  -37.667414521786434
                ],
                [
                  144.76650094934752,
                  -37.672441344700964
                ],
                [
                  144.76648910533032,
                  -37.67276797083058
                ],
                [
                  144.76640169035505,
                  -37.67308732067552
                ],
                [
                  144.76624167699407,
                  -37.67338853481084
                ],
                [
                  144.76601450654965,
                  -37.67366137063968
                ],
                [
                  144.7590489123732,
                  -37.680548589859384
                ]
              ]
            ]
          }
        },
        "ImpactedArea": [
          [
            {
              "Latitude": -37.680548589859384,
              "Longitude": 144.7590489123732
            },
            {
              "Latitude": -37.680811038514506,
              "Longitude": 144.75872129846167
            },
            {
              "Latitude": -37.68101410130429,
              "Longitude": 144.7583321120861
            },
            {
              "Latitude": -37.681148974481914,
              "Longitude": 144.7578982273339
            },
            {
              "Latitude": -37.681209810686944,
              "Longitude": 144.75743845629526
            },
            {
              "Latitude": -37.6811939724059,
              "Longitude": 144.7569727334209
            },
            {
              "Latitude": -37.67662159179456,
              "Longitude": 144.71802128809077
            },
            {
              "Latitude": -37.67653746755044,
              "Longitude": 144.71759652559328
            },
            {
              "Latitude": -37.676389513643166,
              "Longitude": 144.71720057629196
            },
            {
              "Latitude": -37.67618338951141,
              "Longitude": 144.71684858675158
            },
            {
              "Latitude": -37.67592697973994,
              "Longitude": 144.71655402190905
            },
            {
              "Latitude": -37.67563009251197,
              "Longitude": 144.71632814998847
            },
            {
              "Latitude": -37.6753040844793,
              "Longitude": 144.7161796114487
            },
            {
              "Latitude": -37.674961426389686,
              "Longitude": 144.71611408845314
            },
            {
              "Latitude": -37.67461522607846,
              "Longitude": 144.71613408750525
            },
            {
              "Latitude": -37.66027266757495,
              "Longitude": 144.71875619253225
            },
            {
              "Latitude": -37.63430121079435,
              "Longitude": 144.72469701046904
            },
            {
              "Latitude": -37.633964748424184,
              "Longitude": 144.724818269932
            },
            {
              "Latitude": -37.63365369719269,
              "Longitude": 144.72502061017695
            },
            {
              "Latitude": -37.63338017326614,
              "Longitude": 144.72529614983623
            },
            {
              "Latitude": -37.633154831159324,
              "Longitude": 144.72563415634716
            },
            {
              "Latitude": -37.63298644865894,
              "Longitude": 144.72602146399674
            },
            {
              "Latitude": -37.63288158484657,
              "Longitude": 144.72644298674032
            },
            {
              "Latitude": -37.63284432455316,
              "Longitude": 144.72688230581883
            },
            {
              "Latitude": -37.632876119208206,
              "Longitude": 144.72732230928713
            },
            {
              "Latitude": -37.632947783838794,
              "Longitude": 144.72779326428747
            },
            {
              "Latitude": -37.6330329762231,
              "Longitude": 144.72817075630633
            },
            {
              "Latitude": -37.633169073217324,
              "Longitude": 144.72852365706652
            },
            {
              "Latitude": -37.63819610146118,
              "Longitude": 144.7390908756035
            },
            {
              "Latitude": -37.63840422032743,
              "Longitude": 144.73944425474355
            },
            {
              "Latitude": -37.63866309332048,
              "Longitude": 144.73973934608313
            },
            {
              "Latitude": -37.66647495259233,
              "Longitude": 144.76566337106786
            },
            {
              "Latitude": -37.666764312102664,
              "Longitude": 144.76588269652945
            },
            {
              "Latitude": -37.667081333668435,
              "Longitude": 144.7660287540973
            },
            {
              "Latitude": -37.667414521786434,
              "Longitude": 144.76609624771316
            },
            {
              "Latitude": -37.672441344700964,
              "Longitude": 144.76650094934752
            },
            {
              "Latitude": -37.67276797083058,
              "Longitude": 144.76648910533032
            },
            {
              "Latitude": -37.67308732067552,
              "Longitude": 144.76640169035505
            },
            {
              "Latitude": -37.67338853481084,
              "Longitude": 144.76624167699407
            },
            {
              "Latitude": -37.67366137063968,
              "Longitude": 144.76601450654965
            },
            {
              "Latitude": -37.680548589859384,
              "Longitude": 144.7590489123732
            }
          ]
        ],
        "RestorationTime": "2026-07-22T14:34:08",
        "ImpactedCustomers": 35,
        "LocationGeoJson": {
          "type": "Feature",
          "properties": {
            "type": "Historical",
            "customersOff": 35,
            "eventId": "J.26.0142896",
            "startTime": "2026-07-22T08:47:51",
            "restoreTime": "2026-07-22T14:34:08",
            "suburbs": [
              {
                "suburbName": "CALDER PARK",
                "postcode": 3037,
                "streets": [
                  "CALDER FWY"
                ]
              },
              {
                "suburbName": "DIGGERS REST",
                "postcode": 3427,
                "streets": [
                  "CALDER HIGHWAY",
                  "DILLON CT",
                  "HOLDEN RD",
                  "MARK COURT",
                  "THOMPSONS RD"
                ]
              },
              {
                "suburbName": "KEILOR NORTH",
                "postcode": 3036,
                "streets": [
                  "CALDER FREEWAY",
                  "CALDER FWY",
                  "THOMPSONS RD"
                ]
              },
              {
                "suburbName": "PLUMPTON",
                "postcode": 3335,
                "streets": [
                  "HOLDEN RD"
                ]
              }
            ]
          },
          "geometry": {
            "type": "Point",
            "coordinates": [
              144.74130751890033,
              -37.65702706762005
            ]
          }
        },
        "Location": {
          "Latitude": -37.65702706762005,
          "Longitude": 144.74130751890033
        }
      },
      {
        "ImpactedSuburbs": [
          {
            "SuburbName": "DIGGERS REST",
            "PostCode": 3427,
            "Streets": [
              "DIGGERS REST-COIMADAI RD",
              "HOLDEN RD",
              "PLUMPTON RD",
              "ROMEO CT"
            ]
          },
          {
            "SuburbName": "PLUMPTON",
            "PostCode": 3335,
            "Streets": [
              "HOLDEN RD",
              "PLUMPTON RD"
            ]
          }
        ],
        "ImpactedAreaGeoJson": {
          "type": "Feature",
          "properties": {
            "type": "Historical",
            "customersOff": 41,
            "eventId": "J.26.0142896",
            "startTime": "2026-07-22T08:47:51",
            "restoreTime": "2026-07-22T14:34:15",
            "suburbs": [
              {
                "suburbName": "DIGGERS REST",
                "postcode": 3427,
                "streets": [
                  "DIGGERS REST-COIMADAI RD",
                  "HOLDEN RD",
                  "PLUMPTON RD",
                  "ROMEO CT"
                ]
              },
              {
                "suburbName": "PLUMPTON",
                "postcode": 3335,
                "streets": [
                  "HOLDEN RD",
                  "PLUMPTON RD"
                ]
              }
            ]
          },
          "geometry": {
            "type": "Polygon",
            "coordinates": [
              [
                [
                  144.65301199365825,
                  -37.63999359017258
                ],
                [
                  144.65279023630427,
                  -37.63980523311035
                ],
                [
                  144.65206546979377,
                  -37.639119889104165
                ],
                [
                  144.6517023615545,
                  -37.638690645043724
                ],
                [
                  144.6514625685765,
                  -37.63821015182161
                ],
                [
                  144.65135701630507,
                  -37.63770030089532
                ],
                [
                  144.6513905139118,
                  -37.63718432172803
                ],
                [
                  144.65208354891266,
                  -37.633746233100105
                ],
                [
                  144.65219622908106,
                  -37.63337664551771
                ],
                [
                  144.65231457148232,
                  -37.63310823458415
                ],
                [
                  144.65718089866508,
                  -37.62359087782566
                ],
                [
                  144.65748272611594,
                  -37.623142570482486
                ],
                [
                  144.65789603601402,
                  -37.62275402545121
                ],
                [
                  144.65840262547928,
                  -37.622442355979985
                ],
                [
                  144.65898018343887,
                  -37.62222128956714
                ],
                [
                  144.65960327324515,
                  -37.62210056319754
                ],
                [
                  144.66024445294946,
                  -37.62208549436303
                ],
                [
                  144.66083743791881,
                  -37.62212405839766
                ],
                [
                  144.70006250331573,
                  -37.62604763496725
                ],
                [
                  144.70072048305983,
                  -37.62617327091836
                ],
                [
                  144.70132742195676,
                  -37.62641051138386
                ],
                [
                  144.72997633872654,
                  -37.6409336426642
                ],
                [
                  144.73050509950275,
                  -37.64127289200968
                ],
                [
                  144.7309259601155,
                  -37.64169637327625
                ],
                [
                  144.73432839483965,
                  -37.646039977396576
                ],
                [
                  144.73456843573956,
                  -37.64641597948321
                ],
                [
                  144.73472248764335,
                  -37.64681924301083
                ],
                [
                  144.73478588218896,
                  -37.64723754721071
                ],
                [
                  144.7347566982792,
                  -37.64765821571977
                ],
                [
                  144.73222299418552,
                  -37.661687036334556
                ],
                [
                  144.73209932253152,
                  -37.66210396717807
                ],
                [
                  144.73188473578372,
                  -37.662497105242444
                ],
                [
                  144.7315859562522,
                  -37.662854135252104
                ],
                [
                  144.73121234373514,
                  -37.66316387320476
                ],
                [
                  144.71297537322474,
                  -37.67582140170076
                ],
                [
                  144.7124338117072,
                  -37.67612191805444
                ],
                [
                  144.71182325208633,
                  -37.676323192587915
                ],
                [
                  144.71117228223196,
                  -37.67641580197625
                ],
                [
                  144.7105113821182,
                  -37.67639541043368
                ],
                [
                  144.699879522281,
                  -37.675146263391746
                ],
                [
                  144.69926881393332,
                  -37.675022491526796
                ],
                [
                  144.6987031750381,
                  -37.67480219015931
                ],
                [
                  144.69820666641155,
                  -37.67449472953343
                ],
                [
                  144.65301199365825,
                  -37.63999359017258
                ]
              ]
            ]
          }
        },
        "ImpactedArea": [
          [
            {
              "Latitude": -37.63999359017258,
              "Longitude": 144.65301199365825
            },
            {
              "Latitude": -37.63980523311035,
              "Longitude": 144.65279023630427
            },
            {
              "Latitude": -37.639119889104165,
              "Longitude": 144.65206546979377
            },
            {
              "Latitude": -37.638690645043724,
              "Longitude": 144.6517023615545
            },
            {
              "Latitude": -37.63821015182161,
              "Longitude": 144.6514625685765
            },
            {
              "Latitude": -37.63770030089532,
              "Longitude": 144.65135701630507
            },
            {
              "Latitude": -37.63718432172803,
              "Longitude": 144.6513905139118
            },
            {
              "Latitude": -37.633746233100105,
              "Longitude": 144.65208354891266
            },
            {
              "Latitude": -37.63337664551771,
              "Longitude": 144.65219622908106
            },
            {
              "Latitude": -37.63310823458415,
              "Longitude": 144.65231457148232
            },
            {
              "Latitude": -37.62359087782566,
              "Longitude": 144.65718089866508
            },
            {
              "Latitude": -37.623142570482486,
              "Longitude": 144.65748272611594
            },
            {
              "Latitude": -37.62275402545121,
              "Longitude": 144.65789603601402
            },
            {
              "Latitude": -37.622442355979985,
              "Longitude": 144.65840262547928
            },
            {
              "Latitude": -37.62222128956714,
              "Longitude": 144.65898018343887
            },
            {
              "Latitude": -37.62210056319754,
              "Longitude": 144.65960327324515
            },
            {
              "Latitude": -37.62208549436303,
              "Longitude": 144.66024445294946
            },
            {
              "Latitude": -37.62212405839766,
              "Longitude": 144.66083743791881
            },
            {
              "Latitude": -37.62604763496725,
              "Longitude": 144.70006250331573
            },
            {
              "Latitude": -37.62617327091836,
              "Longitude": 144.70072048305983
            },
            {
              "Latitude": -37.62641051138386,
              "Longitude": 144.70132742195676
            },
            {
              "Latitude": -37.6409336426642,
              "Longitude": 144.72997633872654
            },
            {
              "Latitude": -37.64127289200968,
              "Longitude": 144.73050509950275
            },
            {
              "Latitude": -37.64169637327625,
              "Longitude": 144.7309259601155
            },
            {
              "Latitude": -37.646039977396576,
              "Longitude": 144.73432839483965
            },
            {
              "Latitude": -37.64641597948321,
              "Longitude": 144.73456843573956
            },
            {
              "Latitude": -37.64681924301083,
              "Longitude": 144.73472248764335
            },
            {
              "Latitude": -37.64723754721071,
              "Longitude": 144.73478588218896
            },
            {
              "Latitude": -37.64765821571977,
              "Longitude": 144.7347566982792
            },
            {
              "Latitude": -37.661687036334556,
              "Longitude": 144.73222299418552
            },
            {
              "Latitude": -37.66210396717807,
              "Longitude": 144.73209932253152
            },
            {
              "Latitude": -37.662497105242444,
              "Longitude": 144.73188473578372
            },
            {
              "Latitude": -37.662854135252104,
              "Longitude": 144.7315859562522
            },
            {
              "Latitude": -37.66316387320476,
              "Longitude": 144.73121234373514
            },
            {
              "Latitude": -37.67582140170076,
              "Longitude": 144.71297537322474
            },
            {
              "Latitude": -37.67612191805444,
              "Longitude": 144.7124338117072
            },
            {
              "Latitude": -37.676323192587915,
              "Longitude": 144.71182325208633
            },
            {
              "Latitude": -37.67641580197625,
              "Longitude": 144.71117228223196
            },
            {
              "Latitude": -37.67639541043368,
              "Longitude": 144.7105113821182
            },
            {
              "Latitude": -37.675146263391746,
              "Longitude": 144.699879522281
            },
            {
              "Latitude": -37.675022491526796,
              "Longitude": 144.69926881393332
            },
            {
              "Latitude": -37.67480219015931,
              "Longitude": 144.6987031750381
            },
            {
              "Latitude": -37.67449472953343,
              "Longitude": 144.69820666641155
            },
            {
              "Latitude": -37.63999359017258,
              "Longitude": 144.65301199365825
            }
          ]
        ],
        "RestorationTime": "2026-07-22T14:34:15",
        "ImpactedCustomers": 41,
        "LocationGeoJson": {
          "type": "Feature",
          "properties": {
            "type": "Historical",
            "customersOff": 41,
            "eventId": "J.26.0142896",
            "startTime": "2026-07-22T08:47:51",
            "restoreTime": "2026-07-22T14:34:15",
            "suburbs": [
              {
                "suburbName": "DIGGERS REST",
                "postcode": 3427,
                "streets": [
                  "DIGGERS REST-COIMADAI RD",
                  "HOLDEN RD",
                  "PLUMPTON RD",
                  "ROMEO CT"
                ]
              },
              {
                "suburbName": "PLUMPTON",
                "postcode": 3335,
                "streets": [
                  "HOLDEN RD",
                  "PLUMPTON RD"
                ]
              }
            ]
          },
          "geometry": {
            "type": "Point",
            "coordinates": [
              144.69307144924701,
              -37.64925064816964
            ]
          }
        },
        "Location": {
          "Latitude": -37.64925064816964,
          "Longitude": 144.69307144924701
        }
      }
    ]
  },
  {
    "PlannedStartTime": "2026-07-22T07:30:00",
    "PlannedEndTime": "2026-07-22T17:30:00",
    "EventId": "J.26.0141838",
    "Type": "Planned",
    "Status": "Complete",
    "Cause": "Essential Maintenance",
    "StartTime": "2026-07-22T09:20:00",
    "RestorationTime": "2026-07-22T14:56:00",
    "ImpactedCustomers": 38,
    "LocationGeoJson": null,
    "Location": null,
    "ImpactedSuburbs": [],
    "ImpactedAreaGeoJson": null,
    "ImpactedArea": null,
    "LastUpdatedTime": "2026-07-22T05:40:49.237Z",
    "FeedReceivedTime": "2026-07-22T05:18:12.481Z",
    "History": [
      {
        "ImpactedSuburbs": [
          {
            "SuburbName": "HEIDELBERG",
            "PostCode": 3084,
            "Streets": [
              "ALMAY GR",
              "CLEVE GR",
              "MARTIN ST",
              "OLIVE GR"
            ]
          }
        ],
        "ImpactedAreaGeoJson": {
          "type": "Feature",
          "properties": {
            "type": "Historical",
            "customersOff": 38,
            "eventId": "J.26.0141838",
            "startTime": "2026-07-22T09:20:00",
            "restoreTime": "2026-07-22T14:56:00",
            "suburbs": [
              {
                "suburbName": "HEIDELBERG",
                "postcode": 3084,
                "streets": [
                  "ALMAY GR",
                  "CLEVE GR",
                  "MARTIN ST",
                  "OLIVE GR"
                ]
              }
            ]
          },
          "geometry": {
            "type": "Polygon",
            "coordinates": [
              [
                [
                  145.06263337958376,
                  -37.75156319601638
                ],
                [
                  145.06058663312663,
                  -37.75120961004857
                ],
                [
                  145.06054252239903,
                  -37.75116830240236
                ],
                [
                  145.06053320057183,
                  -37.75111474469006
                ],
                [
                  145.0606841666415,
                  -37.75034241833581
                ],
                [
                  145.06072964262307,
                  -37.75030550799545
                ],
                [
                  145.06098246254896,
                  -37.7501908994056
                ],
                [
                  145.06276945894356,
                  -37.749725687500046
                ],
                [
                  145.0631893417502,
                  -37.74977580561595
                ],
                [
                  145.0637703055748,
                  -37.74991643219119
                ],
                [
                  145.06381507421622,
                  -37.74998393872873
                ],
                [
                  145.06388480561978,
                  -37.750708055419
                ],
                [
                  145.0638508801808,
                  -37.75086763388932
                ],
                [
                  145.0635289121966,
                  -37.75147425829103
                ],
                [
                  145.06345728477893,
                  -37.751515056327655
                ],
                [
                  145.0632062610699,
                  -37.751567110613664
                ],
                [
                  145.06295111395323,
                  -37.75159833383232
                ],
                [
                  145.06263337958376,
                  -37.75156319601638
                ]
              ]
            ]
          }
        },
        "ImpactedArea": [
          [
            {
              "Latitude": -37.75156319601638,
              "Longitude": 145.06263337958376
            },
            {
              "Latitude": -37.75120961004857,
              "Longitude": 145.06058663312663
            },
            {
              "Latitude": -37.75116830240236,
              "Longitude": 145.06054252239903
            },
            {
              "Latitude": -37.75111474469006,
              "Longitude": 145.06053320057183
            },
            {
              "Latitude": -37.75034241833581,
              "Longitude": 145.0606841666415
            },
            {
              "Latitude": -37.75030550799545,
              "Longitude": 145.06072964262307
            },
            {
              "Latitude": -37.7501908994056,
              "Longitude": 145.06098246254896
            },
            {
              "Latitude": -37.749725687500046,
              "Longitude": 145.06276945894356
            },
            {
              "Latitude": -37.74977580561595,
              "Longitude": 145.0631893417502
            },
            {
              "Latitude": -37.74991643219119,
              "Longitude": 145.0637703055748
            },
            {
              "Latitude": -37.74998393872873,
              "Longitude": 145.06381507421622
            },
            {
              "Latitude": -37.750708055419,
              "Longitude": 145.06388480561978
            },
            {
              "Latitude": -37.75086763388932,
              "Longitude": 145.0638508801808
            },
            {
              "Latitude": -37.75147425829103,
              "Longitude": 145.0635289121966
            },
            {
              "Latitude": -37.751515056327655,
              "Longitude": 145.06345728477893
            },
            {
              "Latitude": -37.751567110613664,
              "Longitude": 145.0632062610699
            },
            {
              "Latitude": -37.75159833383232,
              "Longitude": 145.06295111395323
            },
            {
              "Latitude": -37.75156319601638,
              "Longitude": 145.06263337958376
            }
          ]
        ],
        "RestorationTime": "2026-07-22T14:56:00",
        "ImpactedCustomers": 38,
        "LocationGeoJson": {
          "type": "Feature",
          "properties": {
            "type": "Historical",
            "customersOff": 38,
            "eventId": "J.26.0141838",
            "startTime": "2026-07-22T09:20:00",
            "restoreTime": "2026-07-22T14:56:00",
            "suburbs": [
              {
                "suburbName": "HEIDELBERG",
                "postcode": 3084,
                "streets": [
                  "ALMAY GR",
                  "CLEVE GR",
                  "MARTIN ST",
                  "OLIVE GR"
                ]
              }
            ]
          },
          "geometry": {
            "type": "Point",
            "coordinates": [
              145.0622090030958,
              -37.75066201066618
            ]
          }
        },
        "Location": {
          "Latitude": -37.75066201066618,
          "Longitude": 145.0622090030958
        }
      }
    ]
  },
  {
    "EstimatedRestorationTime": "2026-07-22T19:21:47",
    "DispatchedTime": "2026-07-22T05:22:49",
    "EventId": "J.26.0144986",
    "Type": "Unplanned",
    "Status": "Acknowledged",
    "Cause": "Under Investigation",
    "StartTime": "2026-07-22T15:21:36",
    "RestorationTime": null,
    "ImpactedCustomers": 16,
    "LocationGeoJson": {
      "type": "Feature",
      "properties": {
        "eventId": "J.26.0144986",
        "customerReference": "",
        "customersOff": "16",
        "status": "Acknowledged",
        "type": "Unplanned",
        "resolvedFlag": "false",
        "showOutageFlag": "true",
        "symptoms": [],
        "cause": "Under Investigation",
        "startTime": "2026-07-22T15:21:36",
        "restoreTime": "",
        "dispatchedTime": "2026-07-22T05:22:49",
        "etr": "2026-07-22T19:21:47",
        "plannedStartTime": "",
        "plannedEndTime": "",
        "lastUpdateTime": "2026-07-22T15:22:49"
      },
      "geometry": {
        "type": "Point",
        "coordinates": [
          144.88927285268818,
          -37.82063098760285
        ]
      }
    },
    "Location": {
      "Latitude": -37.82063098760285,
      "Longitude": 144.88927285268818
    },
    "ImpactedSuburbs": [
      {
        "SuburbName": "YARRAVILLE",
        "PostCode": 3013,
        "Streets": [
          "NEWCASTLE ST"
        ]
      }
    ],
    "ImpactedAreaGeoJson": {
      "type": "Feature",
      "properties": {
        "eventId": "J.26.0144986",
        "customerReference": "",
        "customersOff": "16",
        "status": "Acknowledged",
        "type": "Unplanned",
        "resolvedFlag": "false",
        "showOutageFlag": "true",
        "symptoms": [],
        "cause": "Under Investigation",
        "startTime": "2026-07-22T15:21:36",
        "restoreTime": "",
        "dispatchedTime": "2026-07-22T05:22:49",
        "etr": "2026-07-22T19:21:47",
        "plannedStartTime": "",
        "plannedEndTime": "",
        "lastUpdateTime": "2026-07-22T15:22:49"
      },
      "geometry": {
        "type": "Polygon",
        "coordinates": [
          [
            [
              144.8889288222756,
              -37.82079165413477
            ],
            [
              144.88863810009596,
              -37.820357540938616
            ],
            [
              144.8886660979708,
              -37.820227926380184
            ],
            [
              144.88869277317576,
              -37.82020153500776
            ],
            [
              144.8898696025009,
              -37.82033911714744
            ],
            [
              144.88990760528043,
              -37.82036641252304
            ],
            [
              144.889790773021,
              -37.8210325058747
            ],
            [
              144.88976482050649,
              -37.82106044019793
            ],
            [
              144.8895830007151,
              -37.82104433508695
            ],
            [
              144.8889288222756,
              -37.82079165413477
            ]
          ]
        ]
      }
    },
    "ImpactedArea": [
      [
        {
          "Latitude": -37.82079165413477,
          "Longitude": 144.8889288222756
        },
        {
          "Latitude": -37.820357540938616,
          "Longitude": 144.88863810009596
        },
        {
          "Latitude": -37.820227926380184,
          "Longitude": 144.8886660979708
        },
        {
          "Latitude": -37.82020153500776,
          "Longitude": 144.88869277317576
        },
        {
          "Latitude": -37.82033911714744,
          "Longitude": 144.8898696025009
        },
        {
          "Latitude": -37.82036641252304,
          "Longitude": 144.88990760528043
        },
        {
          "Latitude": -37.8210325058747,
          "Longitude": 144.889790773021
        },
        {
          "Latitude": -37.82106044019793,
          "Longitude": 144.88976482050649
        },
        {
          "Latitude": -37.82104433508695,
          "Longitude": 144.8895830007151
        },
        {
          "Latitude": -37.82079165413477,
          "Longitude": 144.8889288222756
        }
      ]
    ],
    "LastUpdatedTime": "2026-07-22T05:40:49.237Z",
    "FeedReceivedTime": "2026-07-22T05:23:07.558Z",
    "History": null
  },
  {
    "PlannedStartTime": "2026-07-22T08:00:00",
    "PlannedEndTime": "2026-07-22T17:30:00",
    "EventId": "J.26.0143250",
    "Type": "Planned",
    "Status": "Complete",
    "Cause": "Essential Maintenance",
    "StartTime": "2026-07-22T08:04:00",
    "RestorationTime": "2026-07-22T13:53:00",
    "ImpactedCustomers": 105,
    "LocationGeoJson": null,
    "Location": null,
    "ImpactedSuburbs": [],
    "ImpactedAreaGeoJson": null,
    "ImpactedArea": null,
    "LastUpdatedTime": "2026-07-22T05:40:49.237Z",
    "FeedReceivedTime": "2026-07-22T05:33:28.586Z",
    "History": [
      {
        "ImpactedSuburbs": [
          {
            "SuburbName": "ALPHINGTON",
            "PostCode": 3078,
            "Streets": [
              "BENNETT ST",
              "BENNETT STREET",
              "KELVIN RD",
              "PARKLANDS AV",
              "YARANA RD"
            ]
          }
        ],
        "ImpactedAreaGeoJson": {
          "type": "Feature",
          "properties": {
            "type": "Historical",
            "customersOff": 95,
            "eventId": "J.26.0143250",
            "startTime": "2026-07-22T08:04:00",
            "restoreTime": "2026-07-22T13:36:00",
            "suburbs": [
              {
                "suburbName": "ALPHINGTON",
                "postcode": 3078,
                "streets": [
                  "BENNETT ST",
                  "BENNETT STREET",
                  "KELVIN RD",
                  "PARKLANDS AV",
                  "YARANA RD"
                ]
              }
            ]
          },
          "geometry": {
            "type": "Polygon",
            "coordinates": [
              [
                [
                  145.03098940712567,
                  -37.7777492744498
                ],
                [
                  145.03086958785096,
                  -37.777707391920195
                ],
                [
                  145.0298975429366,
                  -37.77705421523981
                ],
                [
                  145.02984141559267,
                  -37.776998041629824
                ],
                [
                  145.02981700238382,
                  -37.77692911251811
                ],
                [
                  145.03013205105938,
                  -37.77491075784884
                ],
                [
                  145.03093230943915,
                  -37.77297613054928
                ],
                [
                  145.0310381008934,
                  -37.77290079305356
                ],
                [
                  145.03148860405773,
                  -37.77282085990993
                ],
                [
                  145.03204142810247,
                  -37.772855376294714
                ],
                [
                  145.0341710814751,
                  -37.77341924616254
                ],
                [
                  145.03425571725026,
                  -37.77345951581483
                ],
                [
                  145.03433427400785,
                  -37.773569529444856
                ],
                [
                  145.034554916436,
                  -37.77405645904836
                ],
                [
                  145.03465220443368,
                  -37.77432695503803
                ],
                [
                  145.03472382633197,
                  -37.77461256608574
                ],
                [
                  145.03442066699571,
                  -37.77626342932552
                ],
                [
                  145.03438604621138,
                  -37.77633562777328
                ],
                [
                  145.03431669954108,
                  -37.77639000656695
                ],
                [
                  145.0315855421345,
                  -37.777767254167024
                ],
                [
                  145.03147215374906,
                  -37.77779565548764
                ],
                [
                  145.03098940712567,
                  -37.7777492744498
                ]
              ]
            ]
          }
        },
        "ImpactedArea": [
          [
            {
              "Latitude": -37.7777492744498,
              "Longitude": 145.03098940712567
            },
            {
              "Latitude": -37.777707391920195,
              "Longitude": 145.03086958785096
            },
            {
              "Latitude": -37.77705421523981,
              "Longitude": 145.0298975429366
            },
            {
              "Latitude": -37.776998041629824,
              "Longitude": 145.02984141559267
            },
            {
              "Latitude": -37.77692911251811,
              "Longitude": 145.02981700238382
            },
            {
              "Latitude": -37.77491075784884,
              "Longitude": 145.03013205105938
            },
            {
              "Latitude": -37.77297613054928,
              "Longitude": 145.03093230943915
            },
            {
              "Latitude": -37.77290079305356,
              "Longitude": 145.0310381008934
            },
            {
              "Latitude": -37.77282085990993,
              "Longitude": 145.03148860405773
            },
            {
              "Latitude": -37.772855376294714,
              "Longitude": 145.03204142810247
            },
            {
              "Latitude": -37.77341924616254,
              "Longitude": 145.0341710814751
            },
            {
              "Latitude": -37.77345951581483,
              "Longitude": 145.03425571725026
            },
            {
              "Latitude": -37.773569529444856,
              "Longitude": 145.03433427400785
            },
            {
              "Latitude": -37.77405645904836,
              "Longitude": 145.034554916436
            },
            {
              "Latitude": -37.77432695503803,
              "Longitude": 145.03465220443368
            },
            {
              "Latitude": -37.77461256608574,
              "Longitude": 145.03472382633197
            },
            {
              "Latitude": -37.77626342932552,
              "Longitude": 145.03442066699571
            },
            {
              "Latitude": -37.77633562777328,
              "Longitude": 145.03438604621138
            },
            {
              "Latitude": -37.77639000656695,
              "Longitude": 145.03431669954108
            },
            {
              "Latitude": -37.777767254167024,
              "Longitude": 145.0315855421345
            },
            {
              "Latitude": -37.77779565548764,
              "Longitude": 145.03147215374906
            },
            {
              "Latitude": -37.7777492744498,
              "Longitude": 145.03098940712567
            }
          ]
        ],
        "RestorationTime": "2026-07-22T13:36:00",
        "ImpactedCustomers": 95,
        "LocationGeoJson": {
          "type": "Feature",
          "properties": {
            "type": "Historical",
            "customersOff": 95,
            "eventId": "J.26.0143250",
            "startTime": "2026-07-22T08:04:00",
            "restoreTime": "2026-07-22T13:36:00",
            "suburbs": [
              {
                "suburbName": "ALPHINGTON",
                "postcode": 3078,
                "streets": [
                  "BENNETT ST",
                  "BENNETT STREET",
                  "KELVIN RD",
                  "PARKLANDS AV",
                  "YARANA RD"
                ]
              }
            ]
          },
          "geometry": {
            "type": "Point",
            "coordinates": [
              145.0322704143579,
              -37.77530825769878
            ]
          }
        },
        "Location": {
          "Latitude": -37.77530825769878,
          "Longitude": 145.0322704143579
        }
      },
      {
        "ImpactedSuburbs": [
          {
            "SuburbName": "ALPHINGTON",
            "PostCode": 3078,
            "Streets": [
              "WINGROVE ST"
            ]
          }
        ],
        "ImpactedAreaGeoJson": {
          "type": "Feature",
          "properties": {
            "type": "Historical",
            "customersOff": 8,
            "eventId": "J.26.0143250",
            "startTime": "2026-07-22T08:04:00",
            "restoreTime": "2026-07-22T13:36:36",
            "suburbs": [
              {
                "suburbName": "ALPHINGTON",
                "postcode": 3078,
                "streets": [
                  "WINGROVE ST"
                ]
              }
            ]
          },
          "geometry": {
            "type": "Polygon",
            "coordinates": [
              [
                [
                  145.03144430871433,
                  -37.777879901922866
                ],
                [
                  145.03089510621413,
                  -37.778067996090144
                ],
                [
                  145.0308626630426,
                  -37.77805504558723
                ],
                [
                  145.03091697499437,
                  -37.777724785756874
                ],
                [
                  145.03100859653236,
                  -37.777551405264475
                ],
                [
                  145.03117231907342,
                  -37.77756517865131
                ],
                [
                  145.03147566813834,
                  -37.77762854826656
                ],
                [
                  145.03144430871433,
                  -37.777879901922866
                ]
              ]
            ]
          }
        },
        "ImpactedArea": [
          [
            {
              "Latitude": -37.777879901922866,
              "Longitude": 145.03144430871433
            },
            {
              "Latitude": -37.778067996090144,
              "Longitude": 145.03089510621413
            },
            {
              "Latitude": -37.77805504558723,
              "Longitude": 145.0308626630426
            },
            {
              "Latitude": -37.777724785756874,
              "Longitude": 145.03091697499437
            },
            {
              "Latitude": -37.777551405264475,
              "Longitude": 145.03100859653236
            },
            {
              "Latitude": -37.77756517865131,
              "Longitude": 145.03117231907342
            },
            {
              "Latitude": -37.77762854826656,
              "Longitude": 145.03147566813834
            },
            {
              "Latitude": -37.777879901922866,
              "Longitude": 145.03144430871433
            }
          ]
        ],
        "RestorationTime": "2026-07-22T13:36:36",
        "ImpactedCustomers": 8,
        "LocationGeoJson": {
          "type": "Feature",
          "properties": {
            "type": "Historical",
            "customersOff": 8,
            "eventId": "J.26.0143250",
            "startTime": "2026-07-22T08:04:00",
            "restoreTime": "2026-07-22T13:36:36",
            "suburbs": [
              {
                "suburbName": "ALPHINGTON",
                "postcode": 3078,
                "streets": [
                  "WINGROVE ST"
                ]
              }
            ]
          },
          "geometry": {
            "type": "Point",
            "coordinates": [
              145.03116916559048,
              -37.77780970067731
            ]
          }
        },
        "Location": {
          "Latitude": -37.77780970067731,
          "Longitude": 145.03116916559048
        }
      }
    ]
  },
  {
    "PlannedStartTime": "2026-07-22T08:00:00",
    "PlannedEndTime": "2026-07-22T17:30:00",
    "EventId": "J.26.0141176",
    "Type": "Planned",
    "Status": "Complete",
    "Cause": "Essential Maintenance",
    "StartTime": "2026-07-22T08:40:00",
    "RestorationTime": "2026-07-22T13:59:00",
    "ImpactedCustomers": 73,
    "LocationGeoJson": null,
    "Location": null,
    "ImpactedSuburbs": [],
    "ImpactedAreaGeoJson": null,
    "ImpactedArea": null,
    "LastUpdatedTime": "2026-07-22T05:40:49.237Z",
    "FeedReceivedTime": "2026-07-22T05:38:33.589Z",
    "History": [
      {
        "ImpactedSuburbs": [
          {
            "SuburbName": "MEADOW HEIGHTS",
            "PostCode": 3048,
            "Streets": [
              "FREEBURGH CT",
              "GLENMAGGIE CT",
              "HALLSTON CT",
              "MELWOOD COURT",
              "MELWOOD CT",
              "TAGGERTY CR"
            ]
          }
        ],
        "ImpactedAreaGeoJson": {
          "type": "Feature",
          "properties": {
            "type": "Historical",
            "customersOff": 73,
            "eventId": "J.26.0141176",
            "startTime": "2026-07-22T08:40:00",
            "restoreTime": "2026-07-22T13:59:00",
            "suburbs": [
              {
                "suburbName": "MEADOW HEIGHTS",
                "postcode": 3048,
                "streets": [
                  "FREEBURGH CT",
                  "GLENMAGGIE CT",
                  "HALLSTON CT",
                  "MELWOOD COURT",
                  "MELWOOD CT",
                  "TAGGERTY CR"
                ]
              }
            ]
          },
          "geometry": {
            "type": "Polygon",
            "coordinates": [
              [
                [
                  144.92037124131767,
                  -37.65900571885272
                ],
                [
                  144.92018893416395,
                  -37.65892813036726
                ],
                [
                  144.92014852707095,
                  -37.658864644506416
                ],
                [
                  144.92014906535687,
                  -37.65881689308044
                ],
                [
                  144.9207533378622,
                  -37.65644707173679
                ],
                [
                  144.9207909954283,
                  -37.65638770647398
                ],
                [
                  144.92093141338052,
                  -37.65626388929032
                ],
                [
                  144.92103375100865,
                  -37.65622264519722
                ],
                [
                  144.9214223198994,
                  -37.65629792293589
                ],
                [
                  144.92304517141014,
                  -37.656756240892
                ],
                [
                  144.9242740684166,
                  -37.65800158442464
                ],
                [
                  144.9243598556042,
                  -37.65812301314501
                ],
                [
                  144.9244973327789,
                  -37.65848676199815
                ],
                [
                  144.92445364824238,
                  -37.65863553645606
                ],
                [
                  144.9242049871906,
                  -37.65886234667067
                ],
                [
                  144.92373326672893,
                  -37.659013364577504
                ],
                [
                  144.92113294849827,
                  -37.65927832385809
                ],
                [
                  144.92037124131767,
                  -37.65900571885272
                ]
              ]
            ]
          }
        },
        "ImpactedArea": [
          [
            {
              "Latitude": -37.65900571885272,
              "Longitude": 144.92037124131767
            },
            {
              "Latitude": -37.65892813036726,
              "Longitude": 144.92018893416395
            },
            {
              "Latitude": -37.658864644506416,
              "Longitude": 144.92014852707095
            },
            {
              "Latitude": -37.65881689308044,
              "Longitude": 144.92014906535687
            },
            {
              "Latitude": -37.65644707173679,
              "Longitude": 144.9207533378622
            },
            {
              "Latitude": -37.65638770647398,
              "Longitude": 144.9207909954283
            },
            {
              "Latitude": -37.65626388929032,
              "Longitude": 144.92093141338052
            },
            {
              "Latitude": -37.65622264519722,
              "Longitude": 144.92103375100865
            },
            {
              "Latitude": -37.65629792293589,
              "Longitude": 144.9214223198994
            },
            {
              "Latitude": -37.656756240892,
              "Longitude": 144.92304517141014
            },
            {
              "Latitude": -37.65800158442464,
              "Longitude": 144.9242740684166
            },
            {
              "Latitude": -37.65812301314501,
              "Longitude": 144.9243598556042
            },
            {
              "Latitude": -37.65848676199815,
              "Longitude": 144.9244973327789
            },
            {
              "Latitude": -37.65863553645606,
              "Longitude": 144.92445364824238
            },
            {
              "Latitude": -37.65886234667067,
              "Longitude": 144.9242049871906
            },
            {
              "Latitude": -37.659013364577504,
              "Longitude": 144.92373326672893
            },
            {
              "Latitude": -37.65927832385809,
              "Longitude": 144.92113294849827
            },
            {
              "Latitude": -37.65900571885272,
              "Longitude": 144.92037124131767
            }
          ]
        ],
        "RestorationTime": "2026-07-22T13:59:00",
        "ImpactedCustomers": 73,
        "LocationGeoJson": {
          "type": "Feature",
          "properties": {
            "type": "Historical",
            "customersOff": 73,
            "eventId": "J.26.0141176",
            "startTime": "2026-07-22T08:40:00",
            "restoreTime": "2026-07-22T13:59:00",
            "suburbs": [
              {
                "suburbName": "MEADOW HEIGHTS",
                "postcode": 3048,
                "streets": [
                  "FREEBURGH CT",
                  "GLENMAGGIE CT",
                  "HALLSTON CT",
                  "MELWOOD COURT",
                  "MELWOOD CT",
                  "TAGGERTY CR"
                ]
              }
            ]
          },
          "geometry": {
            "type": "Point",
            "coordinates": [
              144.92232292992492,
              -37.657750484527654
            ]
          }
        },
        "Location": {
          "Latitude": -37.657750484527654,
          "Longitude": 144.92232292992492
        }
      }
    ]
  }
]